{
    "base_id": "GFSA04",
    "filament_flow_ratio": [
        "0.98"
    ],
    "filament_max_volumetric_speed": [
        "11.0"
    ],
    "filament_settings_id": [
        "GTMax PETG K2"
    ],
    "from": "User",
    "hot_plate_temp": [
        "80"
    ],
    "hot_plate_temp_initial_layer": [
        "85"
    ],
    "inherits": "Hyper PLA @Creality K2 0.4 nozzle",
    "is_custom_defined": "0",
    "name": "GTMax PETG K2",
    "nozzle_temperature_initial_layer": [
        "245"
    ],
    "nozzle_temperature_range_low": [
        "235"
    ],
    "nozzle_temperature_range_high": [
        "255"
    ],
    "textured_plate_temp": [
        "80"
    ],
    "textured_plate_temp_initial_layer": [
        "85"
    ],
    "version": "26.4.28.18"
}